{
  "project_info": {
    "project_number": "543116269827",
    "project_id": "flex-chat-d996e",
    "storage_bucket": "flex-chat-d996e.appspot.com"
  },
  "client": [
    {
      "client_info": {
        "mobilesdk_app_id": "1:543116269827:android:53fa1b9c83cf4eba587136",
        "android_client_info": {
          "package_name": "com.onirutla.flexchat"
        }
      },
      "oauth_client": [
        {
          "client_id": "543116269827-mlp3gfm76q1gjvqrj3k6dg808cb5r221.apps.googleusercontent.com",
          "client_type": 3
        }
      ],
      "api_key": [
        {
          "current_key": "AIzaSyCBsz55e8OkSKRtlMg8LZRgtoXbJTZbzWk"
        }
      ],
      "services": {
        "appinvite_service": {
          "other_platform_oauth_client": [
            {
              "client_id": "543116269827-mlp3gfm76q1gjvqrj3k6dg808cb5r221.apps.googleusercontent.com",
              "client_type": 3
            }
          ]
        }
      }
    }
  ],
  "configuration_version": "1"
}